{
  "collectionName": "components_elements_gmaps",
  "info": {
    "displayName": "Google Map",
    "description": ""
  },
  "options": {},
  "attributes": {
    "name": {
      "type": "string"
    },
    "markerText": {
      "type": "string"
    },
    "markerImage": {
      "type": "media",
      "multiple": false,
      "required": false,
      "allowedTypes": ["images"]
    },
    "lat": {
      "type": "float",
      "default": "34.995602296642474"
    },
    "lng": {
      "type": "float",
      "default": "-85.24814656512154"
    },
    "richtext": {
      "type": "customField",
      "options": {
        "preset": "toolbarBaloon"
      },
      "customField": "plugin::ckeditor5.CKEditor"
    },
    "zoom": {
      "type": "integer",
      "required": false,
      "default": 16
    }
  }
}
